dashai_test_image_classification_plugin_2/__init__.py
dashai_test_image_classification_plugin_2/image_classification_model.py
dashai_test_image_classification_plugin_2/image_classification_task.py
dashai_test_image_classification_plugin_2/image_dataloader.py
dashai_test_image_classification_plugin_2/mlp_image_classifier.py
dashai_test_image_classification_plugin_2-0.0.7.dist-info/METADATA
dashai_test_image_classification_plugin_2-0.0.7.dist-info/WHEEL
dashai_test_image_classification_plugin_2-0.0.7.dist-info/entry_points.txt
dashai_test_image_classification_plugin_2-0.0.7.dist-info/RECORD
